paycomuz/__init__.py
paycomuz/admin.py
paycomuz/apps.py
paycomuz/authentication.py
paycomuz/methods_subscribe_api.py
paycomuz/models.py
paycomuz/status.py
paycomuz/views.py
paycomuz/management/__init__.py
paycomuz/management/commands/__init__.py
paycomuz/management/commands/create_paycom_user.py
paycomuz/migrations/0001_initial.py
paycomuz/migrations/0002_auto_20200111_1714.py
paycomuz/migrations/0003_auto_20210303_2348.py
paycomuz/migrations/0004_auto_20210304_0101.py
paycomuz/migrations/__init__.py
paycomuz/serializers/__init__.py
paycomuz/serializers/payme_operation.py
PaycomUz-3.0.dist-info/LICENSE
PaycomUz-3.0.dist-info/METADATA
PaycomUz-3.0.dist-info/WHEEL
PaycomUz-3.0.dist-info/top_level.txt
PaycomUz-3.0.dist-info/RECORD
