Metadata-Version: 2.1
Name: PaycomUz
Version: 3.0
Summary: Paycomuz
Home-page: https://github.com/begyy/PaycomUz
Author: Sadullayev Bekhzod
Author-email: begymrx@gmail.com
License: UNKNOWN
Platform: UNKNOWN
Classifier: Programming Language :: Python :: 3
Classifier: License :: OSI Approved :: MIT License
Requires-Python: >=3.5
Requires-Dist: requests
Requires-Dist: django
Requires-Dist: djangorestframework
